moriarty/__init__.py
moriarty/adapters/__init__.py
moriarty/agent/__init__.py
moriarty/assets/modules/.gitkeep
moriarty/assets/modules/behance.yaml
moriarty/assets/modules/dribbble.yaml
moriarty/assets/modules/github.yaml
moriarty/assets/modules/gitlab.yaml
moriarty/assets/modules/instagram.yaml
moriarty/assets/modules/linkedin.yaml
moriarty/assets/modules/medium.yaml
moriarty/assets/modules/pinterest.yaml
moriarty/assets/modules/reddit.yaml
moriarty/assets/modules/stackoverflow.yaml
moriarty/assets/modules/steam.yaml
moriarty/assets/modules/tumblr.yaml
moriarty/assets/modules/twitch.yaml
moriarty/assets/modules/twitter.yaml
moriarty/assets/modules/youtube.yaml
moriarty/assets/modules/asia/douban.yaml
moriarty/assets/modules/asia/kakao.yaml
moriarty/assets/modules/asia/line.yaml
moriarty/assets/modules/asia/mixi.yaml
moriarty/assets/modules/asia/naver.yaml
moriarty/assets/modules/asia/qq.yaml
moriarty/assets/modules/asia/vk.yaml
moriarty/assets/modules/asia/wechat.yaml
moriarty/assets/modules/asia/weibo.yaml
moriarty/assets/modules/asia/xiaohongshu.yaml
moriarty/assets/modules/business/crunchbase.yaml
moriarty/assets/modules/business/fiverr.yaml
moriarty/assets/modules/business/freelancer.yaml
moriarty/assets/modules/business/glassdoor.yaml
moriarty/assets/modules/business/guru.yaml
moriarty/assets/modules/business/indeed.yaml
moriarty/assets/modules/business/monster.yaml
moriarty/assets/modules/business/peopleperhour.yaml
moriarty/assets/modules/business/toptal.yaml
moriarty/assets/modules/business/upwork.yaml
moriarty/assets/modules/business/ziprecruiter.yaml
moriarty/assets/modules/content/buymeacoffee.yaml
moriarty/assets/modules/content/gumroad.yaml
moriarty/assets/modules/content/ko-fi.yaml
moriarty/assets/modules/content/onlyfans.yaml
moriarty/assets/modules/content/patreon.yaml
moriarty/assets/modules/content/substack.yaml
moriarty/assets/modules/creative/500px.yaml
moriarty/assets/modules/creative/artstation.yaml
moriarty_project-0.1.27.dist-info/METADATA
moriarty_project-0.1.27.dist-info/WHEEL
moriarty_project-0.1.27.dist-info/entry_points.txt
moriarty_project-0.1.27.dist-info/RECORD
