Metadata-Version: 2.4
Name: moriarty-project
Version: 0.1.27
Summary: Client-side OSINT toolkit with forensic-grade evidence handling.
Project-URL: Homepage, https://github.com/DonatoReis/moriarty
Project-URL: Documentation, https://github.com/DonatoReis/moriarty#readme
Author: Moriarty Contributors
License: MIT
Keywords: cli,forensics,osint,security
Classifier: Intended Audience :: Information Technology
Classifier: License :: OSI Approved :: MIT License
Classifier: Programming Language :: Python
Classifier: Programming Language :: Python :: 3
Classifier: Programming Language :: Python :: 3 :: Only
Classifier: Programming Language :: Python :: 3.11
Classifier: Programming Language :: Python :: 3.12
Classifier: Programming Language :: Python :: 3.13
Classifier: Topic :: Security
Classifier: Topic :: Utilities
Requires-Python: >=3.11
Requires-Dist: aiodns>=3.0.0
Requires-Dist: aiofiles>=24.1.0
Requires-Dist: aiohttp>=3.9.0
Requires-Dist: aiolimiter>=1.1.0
Requires-Dist: aiosmtplib>=2.0.0
Requires-Dist: colorama>=0.4.6
Requires-Dist: dnspython>=2.5.0
Requires-Dist: email-validator>=2.0.0
Requires-Dist: httpx[http2]>=0.27.0
Requires-Dist: idna>=3.6
Requires-Dist: jsonpath-ng>=1.6.0
Requires-Dist: lxml>=5.3.0
Requires-Dist: netifaces-plus>=0.12.4
Requires-Dist: networkx>=3.2.0
Requires-Dist: orjson>=3.9.0
Requires-Dist: packaging>=25.0
Requires-Dist: phonenumbers>=8.13.0
Requires-Dist: pillow>=10.0.0
Requires-Dist: psutil>=5.9.0
Requires-Dist: pycryptodomex>=3.23.0
Requires-Dist: pydantic>=2.7.0
Requires-Dist: pyopenssl>=25.0.0
Requires-Dist: python3-nmap>=1.9.1
Requires-Dist: pyyaml>=6.0
Requires-Dist: rapidfuzz>=3.0.0
Requires-Dist: requests>=2.32.0
Requires-Dist: rich>=13.7.0
Requires-Dist: scapy>=2.5.0
Requires-Dist: selectolax>=0.3.20
Requires-Dist: structlog>=24.1.0
Requires-Dist: tqdm>=4.67.0
Requires-Dist: typer[all]>=0.12.0
Requires-Dist: uvloop>=0.19.0; platform_system != 'Windows'
Provides-Extra: capture
Requires-Dist: pypcap>=1.2.3; (platform_system == 'Linux' or platform_system == 'Windows') and extra == 'capture'
Requires-Dist: python-libpcap>=0.5; (platform_system == 'Darwin') and extra == 'capture'
Requires-Dist: python-wifi>=0.6.1; (platform_system == 'Linux' or platform_system == 'Windows') and extra == 'capture'
Requires-Dist: pywifi>=1.1.12; (platform_system == 'Linux' or platform_system == 'Windows') and extra == 'capture'
Provides-Extra: dev
Requires-Dist: cyclonedx-bom>=4.4.0; extra == 'dev'
Requires-Dist: deptry>=0.23.0; extra == 'dev'
Requires-Dist: hypothesis>=6.98.0; extra == 'dev'
Requires-Dist: mypy>=1.10.0; extra == 'dev'
Requires-Dist: pip-audit>=2.7.0; extra == 'dev'
Requires-Dist: pytest-xdist>=3.5.0; extra == 'dev'
Requires-Dist: pytest>=8.0.0; extra == 'dev'
Requires-Dist: ruff>=0.5.0; extra == 'dev'
Provides-Extra: headless
Requires-Dist: playwright>=1.40.0; extra == 'headless'
Provides-Extra: http3
Requires-Dist: aioquic>=0.9.0; extra == 'http3'
Provides-Extra: image
Requires-Dist: imagehash>=4.3.0; extra == 'image'
Provides-Extra: pdf
Requires-Dist: weasyprint>=60.0; extra == 'pdf'
Provides-Extra: sign
Requires-Dist: sigstore>=2.0.0; extra == 'sign'
Provides-Extra: stix
Requires-Dist: stix2>=3.0.0; extra == 'stix'
